ex_cd/__init__.py
ex_cd/__main__.py
ex_cd/collect.py
ex_cd/common.py
ex_cd/config.py
ex_cd/deprecate.py
ex_cd/download.py
ex_cd/gallery_dl_exec.py
ex_cd/history.py
ex_cd/meta.py
ex_cd/output.py
ex_cd/validate.py
ex_cd/tools/__init__.py
ex_cd/tools/__main__.py
ex_cd/tools/config.py
ex_cd/tools/delete.py
ex_cd/tools/latest_meta.py
ex_cd-1.17.1.dist-info/licenses/LICENSE
ex_cd-1.17.1.dist-info/METADATA
ex_cd-1.17.1.dist-info/WHEEL
ex_cd-1.17.1.dist-info/top_level.txt
ex_cd-1.17.1.dist-info/RECORD
