Metadata-Version: 2.4
Name: ex_cd
Version: 1.17.1
Summary: 高效下载E站gallery的所有历史数据
Author-email: yindaheng98 <yindaheng98@163.com>
License: MIT
Project-URL: Homepage, https://github.com/yindaheng98/ex-cd
Project-URL: Repository, https://github.com/yindaheng98/ex-cd
Classifier: Programming Language :: Python :: 3
Classifier: License :: OSI Approved :: MIT License
Classifier: Operating System :: OS Independent
Requires-Python: >=3.7
License-File: LICENSE
Requires-Dist: gallery-dl
Dynamic: license-file
